[{"id":3,"title":"producto 3","description":"descripcion 3","price":3020,"thumbnails":["1","2","3"],"code":"code3","stock":10,"status":"true","category":"almacen"},{"id":4,"title":"producto 4","description":"descripcion 4","price":3420,"thumbnails":["1","2","3"],"code":"code4","stock":10,"status":"true","category":"almacen"},{"id":5,"title":"producto 5","description":"descripcion 5","price":3425,"thumbnails":["1","2","3"],"code":"code5","stock":10,"status":"true","category":"almacen"},{"id":6,"title":"producto 6","description":"descripcion 6","price":34,"thumbnails":["1","2","3"],"code":"code6","stock":10,"status":"true","category":"almacen"},{"id":7,"title":"producto 7","description":"descripcion 7","price":3442,"thumbnails":["1","2","3"],"code":"code7","stock":10,"status":"true","category":"almacen"},{"id":8,"title":"producto 8","description":"descripcion 8","price":1500,"thumbnails":["1","2","3"],"code":"code8","stock":10,"status":"true","category":"almacen"},{"id":9,"title":"producto 9","description":"descripcion 9","price":5541,"thumbnails":["1","2","3"],"code":"code9","stock":10,"status":"true","category":"almacen"},{"id":10,"title":"asda","description":"123","price":"123","thumbnails":{},"code":"123","stock":"123","status":true,"category":"123"}]